README.txt
setup.cfg
setup.py
AnalyticMicroService/__init__.py
AnalyticMicroService.egg-info/PKG-INFO
AnalyticMicroService.egg-info/SOURCES.txt
AnalyticMicroService.egg-info/dependency_links.txt
AnalyticMicroService.egg-info/top_level.txt
AnalyticMicroService/cli/AMSCommandLine.py
AnalyticMicroService/cli/__init__.py
AnalyticMicroService/cli/modules/AMSCommandRunner.py
AnalyticMicroService/cli/modules/AMSCommandRunnerConfig.py
AnalyticMicroService/cli/modules/__init__.py
AnalyticMicroService/cli/tests/TestCommandLine.py
AnalyticMicroService/cli/tests/__init__.py
AnalyticMicroService/examples/__init__.py
AnalyticMicroService/examples/ACExample1/ACExample1.py
AnalyticMicroService/examples/ACExample1/RunACExample1.py
AnalyticMicroService/examples/ACExample1/__init__.py
AnalyticMicroService/server/__init__.py
AnalyticMicroService/server/app/AMSapp.py
AnalyticMicroService/server/app/__init__.py
AnalyticMicroService/server/modules/__init__.py
AnalyticMicroService/server/routes/AMSSimpleRoute.py
AnalyticMicroService/server/routes/__init__.py
AnalyticMicroService/server/tests/TestAMSServer.py
AnalyticMicroService/server/tests/__init__.py
AnalyticMicroService/server/utils/AMSRESTUtils.py
AnalyticMicroService/server/utils/AMSSettings.py
AnalyticMicroService/server/utils/AMSSingletons.py
AnalyticMicroService/server/utils/AMSUserApp.py
AnalyticMicroService/server/utils/__init__.py