Metadata-Version: 1.1
Name: AnalyticMicroService
Version: 0.23
Summary: Analytic Micro Service
Home-page: https://github.com/DataKitchen/AnalyticMicroService
Author: datakitchen
Author-email: cbergh@datakitchen.io
License: UNKNOWN
Download-URL: https://github.com/DataKitchen/AnalyticMicroService/tarball/0.21
Keywords: Analytic,microservice,service
Platform: UNKNOWN
